pike_smb2-0.4.0.dist-info/METADATA
pike_smb2-0.4.0.dist-info/LICENSE
pike_smb2-0.4.0.dist-info/WHEEL
pike_smb2-0.4.0.dist-info/top_level.txt
pike_smb2-0.4.0.dist-info/RECORD
pike_smb2-0.4.0.dist-info/entry_points.txt
pike/__init__.py
pike/digest.py
pike/crypto.py
pike/model.py
pike/pytest_support.py
pike/auth.py
pike/nttime.py
pike/smb2.py
pike/transport.py
pike/path.py
pike/kerberos.so
pike/exceptions.py
pike/io.py
pike/netbios.py
pike/core.py
pike/ntstatus.py
pike/ntlm.py
pike/test/__init__.py
pike/test/ioctl.py
pike/test/changenotify.py
pike/test/credit.py
pike/test/query.py
pike/test/invalid_tree.py
pike/test/readwrite.py
pike/test/copychunk.py
pike/test/oplock.py
pike/test/acl.py
pike/test/invalid_session.py
pike/test/negotiate.py
pike/test/echo.py
pike/test/set.py
pike/test/compound.py
pike/test/reparse.py
pike/test/persistent.py
pike/test/lease.py
pike/test/tree.py
pike/test/querydirectory.py
pike/test/session.py
pike/test/encryption.py
pike/test/multichannel.py
pike/test/queryondiskid.py
pike/test/lock.py
pike/test/appinstanceid.py
pike/test/durable.py
pike_smb2.libs/libcom_err-f79b9776.so.2.1
pike_smb2.libs/libgssapi_krb5-bb73e344.so.2.2
pike_smb2.libs/libselinux-d72a37e2.so.1
pike_smb2.libs/libkrb5support-2ce1fd50.so.0.1
pike_smb2.libs/libk5crypto-ab4ddf4c.so.3.1
pike_smb2.libs/libkrb5-7e4170ab.so.3.3
pike_smb2.libs/libkeyutils-68db41cc.so.1.3
