Metadata-Version: 2.1
Name: pike-smb2
Version: 0.4.0
Summary: Pure python SMB client
Home-page: https://github.com/emc-isilon/pike
Author: Brian Koropoff
Author-email: Brian.Koropoff@emc.com
Maintainer: Masen Furer
Maintainer-email: m_github@0x26.net
License: Simplified BSD License
Project-URL: Source, https://github.com/emc-isilon/pike
Project-URL: Bug Reports, https://github.com/emc-isilon/pike/issues
Keywords: smb,smb-testing,smb-client
Platform: unix
Platform: linux
Platform: osx
Platform: cygwin
Platform: win32
Classifier: Development Status :: 4 - Beta
Classifier: Intended Audience :: Developers
Classifier: Topic :: Software Development :: Testing
Classifier: Programming Language :: Python
Classifier: Programming Language :: Python :: 2
Classifier: Programming Language :: Python :: 2.7
Classifier: Programming Language :: Python :: 3
Classifier: Programming Language :: Python :: 3.6
Classifier: Programming Language :: Python :: 3.7
Classifier: Programming Language :: Python :: 3.8
Classifier: Programming Language :: Python :: 3.9
Classifier: Programming Language :: Python :: 3.10
Classifier: Programming Language :: Python :: Implementation :: CPython
Classifier: Operating System :: OS Independent
Classifier: Environment :: Console
Classifier: License :: OSI Approved :: BSD License
Requires-Python: !=3.0.*,!=3.1.*,!=3.2.*,!=3.3.*,!=3.4.*,!=3.5.*,>=2.7
Requires-Dist: attrs (>=19.3)
Requires-Dist: future
Requires-Dist: pycryptodome
Requires-Dist: six
Requires-Dist: enum34 (~=1.1.6) ; python_version ~= "2.7"
Requires-Dist: pathlib2 (~=2.3.5) ; python_version ~= "2.7"
